nucore_holiday_provider.py
nucore_holiday_provider-1.0.1.dist-info/METADATA
nucore_holiday_provider-1.0.1.dist-info/WHEEL
nucore_holiday_provider-1.0.1.dist-info/top_level.txt
nucore_holiday_provider-1.0.1.dist-info/RECORD
